app/__init__.py
app/auth.py
app/badges.py
app/caching.py
app/config.py
app/misc.py
app/models.py
app/socketio.py
app/sorting.py
app/storage.py
app/forms/__init__.py
app/forms/admin.py
app/forms/sub.py
app/forms/user.py
app/views/__init__.py
app/views/admin.py
app/views/api3.py
app/views/auth.py
app/views/do.py
app/views/errors.py
app/views/home.py
app/views/messages.py
app/views/mod.py
app/views/site.py
app/views/sub.py
app/views/subs.py
app/views/user.py
app/views/wiki.py
test/__init__.py
test/fixtures.py
test/utilities.py
test/specs/__init__.py
test/specs/test_admin.py
test/specs/test_auth.py
test/views/__init__.py
throat-0.0.0.dist-info/LICENSE
throat-0.0.0.dist-info/METADATA
throat-0.0.0.dist-info/WHEEL
throat-0.0.0.dist-info/top_level.txt
throat-0.0.0.dist-info/RECORD
