Metadata-Version: 2.1
Name: throat
Version: 0.0.0
Summary: Open source link aggregator
Home-page: https://github.com/Phuks-co/throat
Author: Phuks LLC
Author-email: admin@phuks.co
License: UNKNOWN
Platform: UNKNOWN
Classifier: Development Status :: 5 - Production/Stable
Classifier: Framework :: Flask
Classifier: Programming Language :: Python :: 3
Classifier: License :: OSI Approved :: MIT License
Classifier: Operating System :: POSIX :: Linux
Requires-Python: >=3.6
